<?xml version="1.0"?>
<gallery>
	<img><![CDATA[gallery_#013 ~01.swf]]></img>
	<img><![CDATA[gallery_#013 ~02.swf]]></img>
	<img><![CDATA[gallery_#013 ~03.swf]]></img>
	<img><![CDATA[gallery_#013 ~04.swf]]></img>
	<img><![CDATA[gallery_#013 ~05.swf]]></img>
	<img><![CDATA[gallery_#013 ~06.swf]]></img>
	<img><![CDATA[gallery_#013 ~07.swf]]></img>
	<img><![CDATA[gallery_#013 ~08.swf]]></img>
	<img><![CDATA[gallery_#013 ~09.swf]]></img>
	<img><![CDATA[gallery_#013 ~10.swf]]></img>
	<img><![CDATA[gallery_#013 ~11.swf]]></img>
	<img><![CDATA[gallery_#013 ~12.swf]]></img>
	<img><![CDATA[gallery_#013 ~13.swf]]></img>
	<img><![CDATA[gallery_#013 ~14.swf]]></img>
	<img><![CDATA[gallery_#013 ~15.swf]]></img>
</gallery>